jianwangceshi2/__init__.py
jianwangceshi2/generator.py
jianwangceshi2-0.1.0.dist-info/LICENSE.txt
jianwangceshi2-0.1.0.dist-info/METADATA
jianwangceshi2-0.1.0.dist-info/WHEEL
jianwangceshi2-0.1.0.dist-info/top_level.txt
jianwangceshi2-0.1.0.dist-info/RECORD
