Metadata-Version: 2.1
Name: jianwangceshi2
Version: 0.1.0
Summary: A tool for generating network files
Home-page: https://github.com/yourusername/network_generator
Author: Your Name
Author-email: your.email@example.com
Classifier: Programming Language :: Python :: 3
Classifier: License :: OSI Approved :: MIT License
Classifier: Operating System :: OS Independent
Requires-Python: >=3.6
License-File: LICENSE.txt
